{
    "tournament_title": "TCK Hallen-LK-Turnier #18",
    "tournament_dates": {
        "tournament_date": "22.03.2025 - 22.03.2025",
        "tournament_registration_start": "26.01.2025, 12:00 Uhr",
        "tournament_registration_end": "19.03.2025, 18:00 Uhr",
        "tournament_draw_date": "19.03.2025, 18:01 Uhr"
    },
    "tournament_location": {
        "tournament_plz": "19.03.2025, 18:01 Uhr",
        "tournament_street": "19.03.2025, 18:01 Uhr"
    },
    "tournament_link": "https://www.tennis.de/spielen/turniersuche.html#detail/681420"
}{
    "tournament_title": "geballt.de Ranglisten-Cup Serie 2025",
    "tournament_dates": {
        "tournament_date": "22.03.2025 - 23.03.2025",
        "tournament_registration_start": "Nicht angegeben",
        "tournament_registration_end": "17.03.2025, 19:00 Uhr",
        "tournament_draw_date": "17.03.2025, 19:30 Uhr"
    },
    "tournament_location": {
        "tournament_plz": "17.03.2025, 19:30 Uhr",
        "tournament_street": "17.03.2025, 19:30 Uhr"
    },
    "tournament_link": "https://www.tennis.de/spielen/turniersuche.html#detail/670640"
}